dtocean_dummy/__init__.py
dtocean_dummy/command.py
dtocean_dummy/config/configuration.ini
dtocean_dummy/config/logging.yaml
dtocean_dummy/config/validation.ini
dtocean_dummy/main.py
dtocean_dummy_module-1.0.0.dist-info/entry_points.txt
dtocean_dummy_module-1.0.0.dist-info/LICENSE
dtocean_dummy_module-1.0.0.dist-info/METADATA
dtocean_dummy_module-1.0.0.dist-info/WHEEL
dtocean_dummy_module-1.0.0.dist-info/RECORD
